{
  "pages": [
    {
      "page": 1,
      "text": "广州住房公积金管理中心\n责令限期办理决定书\n穗公积金中心越秀责字〔2024〕914-1号\n名称：广州市严静殡葬服务有限公司\n统一社会信用代码：91440101MA5C4HHP8E\n地址：广州市越秀区寺右二马路25号四层454\n经查，你单位未按规定为王柱华缴存2022年07月至2023年06月期间的住房公积金。根据《住房公积金管理条例》(1999年4月3日国务院令第262号发\n布施行，2002年3月24日国务院令第350号第一次修订，2019年3月24日国\n务院令第710号第二次修订)第二条、第十三条、第十五条、第十六条、第十七条、\n第十八条、第十九条、第二十条、第三十七条、第三十八条、第四十七条、《关\n于住房公积金管理若干具体问题的指导意见》(建金管[2005]5号)第六条、《关\n于住房公积金管理几个具体问题的通知》(建金管[2006]52号)等有关规定，\n责令你单位履行以下义务：\n请在收到本决定书之日起10个工作日内为你单位王柱华补缴2022年07月\n至2023年06月期间的单位应缴存部分住房公积金合计2748元到职工住房公积",
      "original_text": "广州住房公积金管理中心\n责令限期办理决定书\n穗公积金中心越秀责字【2024]914-1号\n名称：广州市严静殡葬服务有限公司\n统一社会信用代码：91440101MA5C4HHP8E\n地址：广州市越秀区寺右二马路25号四层454\n经查，你单位未按规定为王柱华缴存2022年07月至2023年06月期间的住\n房公积金。根据《住房公积金管理条例》（1999年4月3日国务院令第262号发\n布施行，2002年3月24日国务院令第350号第一次修订，2019年3月24日国\n务院令第710号第二次修订）第二条、第十三条、第十五条、第十六条、第十七条、\n第十八条、第十九条、第二十条、第三十七条、第三十八条、第四十七条、《关\n于住房公积金管理若干具体问题的指导意见》（建金管[2005]5号）第六条、《关\n于住房公积金管理几个具体问题的通知》（建金管【2006】52号）等有关规定，\n责令你单位履行以下义务：\n请在收到本决定书之日起10个工作日内为你单位王柱华补缴2022年07月\n至2023年06月期间的单位应缴存部分住房公积金合计2748元到职工住房公积",
      "method": "region_first",
      "duration": 28.68483328819275,
      "region_attempts": [
        {
          "region": "责令号区域",
          "region_key": "notice_header",
          "method": "region:责令号区域",
          "duration": 28.68483328819275,
          "text_length": 472,
          "text": "广州住房公积金管理中心\n责令限期办理决定书\n穗公积金中心越秀责字【2024]914-1号\n名称：广州市严静殡葬服务有限公司\n统一社会信用代码：91440101MA5C4HHP8E\n地址：广州市越秀区寺右二马路25号四层454\n经查，你单位未按规定为王柱华缴存2022年07月至2023年06月期间的住\n房公积金。根据《住房公积金管理条例》（1999年4月3日国务院令第262号发\n布施行，2002年3月24日国务院令第350号第一次修订，2019年3月24日国\n务院令第710号第二次修订）第二条、第十三条、第十五条、第十六条、第十七条、\n第十八条、第十九条、第二十条、第三十七条、第三十八条、第四十七条、《关\n于住房公积金管理若干具体问题的指导意见》（建金管[2005]5号）第六条、《关\n于住房公积金管理几个具体问题的通知》（建金管【2006】52号）等有关规定，\n责令你单位履行以下义务：\n请在收到本决定书之日起10个工作日内为你单位王柱华补缴2022年07月\n至2023年06月期间的单位应缴存部分住房公积金合计2748元到职工住房公积"
        }
      ],
      "region_stats": {
        "attempt_count": 1,
        "total_duration": 28.6848,
        "max_text_length": 472,
        "total_text_length": 472,
        "regions": [
          "责令号区域"
        ]
      },
      "region_text_length": 457,
      "fallback_used": false,
      "fallback_trigger_reason": null,
      "notice_matched": false,
      "boundary_detected": false,
      "marker_detected": false,
      "region_usable": false
    },
    {
      "page": 2,
      "text": "",
      "original_text": "",
      "method": "blank_page_skipped",
      "duration": 0,
      "region_attempts": [],
      "region_stats": {
        "attempt_count": 0,
        "total_duration": 0,
        "max_text_length": 0,
        "total_text_length": 0,
        "regions": []
      },
      "region_text_length": 0,
      "fallback_used": false,
      "fallback_trigger_reason": null,
      "notice_matched": false,
      "boundary_detected": false,
      "marker_detected": false,
      "region_usable": false
    },
    {
      "page": 3,
      "text": "广州住房公积金管理中心\n住房公积金\n输入关键字搜索\n首页\n信息公开\n工作动态\n通知公告\n办事服务\n下载中心\n业务网点\n互动交流\n当前位置：首页>公告>执法公告\n关于向广州市严静殡葬服务有限公司送达《责令限期办理决定书》的公告\n发布日期：2025-07-0215:11:45来源：本网浏览次数：-字号：大中小",
      "original_text": "广州住房公积金管理中心\n住房公积金\n输入关键字搜索\n首页\n信息公开\n工作动态\n通知公告\n办事服务\n下载中心\n业务网点\n互动交流\n当前位置：首页>公告>执法公告\n关于向广州市严静殡葬服务有限公司送达《责令限期办理\n决定书》的公告\n发布日期：2025-07-0215:11:45来源：本网浏览次数：-字号：大中小",
      "method": "region_first",
      "duration": 11.120157957077026,
      "region_attempts": [
        {
          "region": "责令号区域",
          "region_key": "notice_header",
          "method": "region:责令号区域",
          "duration": 11.120157957077026,
          "text_length": 154,
          "text": "广州住房公积金管理中心\n住房公积金\n输入关键字搜索\n首页\n信息公开\n工作动态\n通知公告\n办事服务\n下载中心\n业务网点\n互动交流\n当前位置：首页>公告>执法公告\n关于向广州市严静殡葬服务有限公司送达《责令限期办理\n决定书》的公告\n发布日期：2025-07-0215:11:45来源：本网浏览次数：-字号：大中小"
        }
      ],
      "region_stats": {
        "attempt_count": 1,
        "total_duration": 11.1202,
        "max_text_length": 154,
        "total_text_length": 154,
        "regions": [
          "责令号区域"
        ]
      },
      "region_text_length": 140,
      "fallback_used": false,
      "fallback_trigger_reason": null,
      "notice_matched": false,
      "boundary_detected": false,
      "marker_detected": false,
      "region_usable": false
    },
    {
      "page": 4,
      "text": "",
      "original_text": "",
      "method": "blank_page_skipped",
      "duration": 0,
      "region_attempts": [],
      "region_stats": {
        "attempt_count": 0,
        "total_duration": 0,
        "max_text_length": 0,
        "total_text_length": 0,
        "regions": []
      },
      "region_text_length": 0,
      "fallback_used": false,
      "fallback_trigger_reason": null,
      "notice_matched": false,
      "boundary_detected": false,
      "marker_detected": false,
      "region_usable": false
    },
    {
      "page": 5,
      "text": "国内特快专递\n客服电话：11183\n网站：www.ens.com.cn\n回共\n月日时\n(住房公积金管\n回\n(通知)\n1285261070703认\n四年00月17日\n受条款的一切内容！\n签名：先生\n理条例、\n指导意见》\nYEDO\n签名\n证件号码：\n1285261070703\nR\nH\n实物退单\n定拾\n保价费：\n其他费用：\n口收件人付\n口月结\n第三方付费口现金\n投递人员：\n元\n投递边收寄递费：\n口电子返单\n费用合计：\n资件入修\n口\n收客人员：\nR",
      "original_text": "国内特快专递\n客服电话：11183\n网站：www.ens.com.cn\n回共\n月日时\n（住房公积金管\n回\n（通知）\n1285261070703认\n四年00月17日\n受条款的一切内容！\n签名：先生\n理条例、\n指导意见》\nYEDO\n签名\n证件号码：\n1285261070703\nR\nH\n实物退单\n定拾\n保价费：\n其他费用：\n口收件人付\n口月结\n第三方付费口现金\n投递人员：\n元\n投递边收寄递费：\n口电子返单\n费用合计：\n资件入修\n口\n收客人员：\nR",
      "method": "region_first",
      "duration": 14.121504545211792,
      "region_attempts": [
        {
          "region": "责令号区域",
          "region_key": "notice_header",
          "method": "region:责令号区域",
          "duration": 14.121504545211792,
          "text_length": 222,
          "text": "国内特快专递\n客服电话：11183\n网站：www.ens.com.cn\n回共\n月日时\n（住房公积金管\n回\n（通知）\n1285261070703认\n四年00月17日\n受条款的一切内容！\n签名：先生\n理条例、\n指导意见》\nYEDO\n签名\n证件号码：\n1285261070703\nR\nH\n实物退单\n定拾\n保价费：\n其他费用：\n口收件人付\n口月结\n第三方付费口现金\n投递人员：\n元\n投递边收寄递费：\n口电子返单\n费用合计：\n资件入修\n口\n收客人员：\nR"
        }
      ],
      "region_stats": {
        "attempt_count": 1,
        "total_duration": 14.1215,
        "max_text_length": 222,
        "total_text_length": 222,
        "regions": [
          "责令号区域"
        ]
      },
      "region_text_length": 187,
      "fallback_used": false,
      "fallback_trigger_reason": null,
      "notice_matched": false,
      "boundary_detected": false,
      "marker_detected": false,
      "region_usable": false
    },
    {
      "page": 6,
      "text": "",
      "original_text": "",
      "method": "blank_page_skipped",
      "duration": 0,
      "region_attempts": [],
      "region_stats": {
        "attempt_count": 0,
        "total_duration": 0,
        "max_text_length": 0,
        "total_text_length": 0,
        "regions": []
      },
      "region_text_length": 0,
      "fallback_used": false,
      "fallback_trigger_reason": null,
      "notice_matched": false,
      "boundary_detected": false,
      "marker_detected": false,
      "region_usable": false
    },
    {
      "page": 7,
      "text": "2025/6/23 10:45\n中国邮政速递物流\n155****9772\nR8ENS\n关作中文\n中国邮政速递物选\n自类产品务\n服苏文行业城决方食民服务制关于我们集站\n奇内地\n邮件号直沟直询能果\n地入,1个级续20个排持号(多个强分空情成与F)\n邮件物迹\n资台\n生\n★☆ 4.91\n+\n邦件号：1285261070703\n在线客服\ns8 -In 0\n不门\n广\n广k\nQ换\n科号查湾\n山市印\nDA\n市\nX5\n20254年\n06月19日\n送中\n09:37广附市，快正在源送中，请形等持，保电法通，准备签者，加有超的动电联快\n12:25\n广图志，您的快件已代签表[寄排人微收]，或为退应坚者件人，如有经电联换通\n员[电话：13922266917]，有事矿线，少一次投银，多感8，中国部改将全心可\n护物的低,质普电话11183,\n诺员[信超母，电话：13322266917]成旗路[电话：020-83818510]，监督电话\n11183,\n时打天17小时\n服务支牌\n送中\n务查调\n案户H下线\n个人\n06月15日\n09:03广附市，快件到达[广热市中区染华烫投部]\n05:07广附击，换件已在[广款空中]完成分，准氨发出\n20:53广账市，软离开[广账市中区东高控控的]，正在发往[广指放空中心]\n20:13广市,续件已程[广的市中区乐追医强投型] 完成分苏,准数出\n17:34广面市，已完成遗跑快件的分技，准备发出\n深送异\n1225广附市，医表片人范衣，快件格延面等件人，知有限与评电联性品[电\n磊：18922183735].股省98电11183,",
      "original_text": "2025/6/23 10:45\n中国邮政速递物流\n155****9772\nR8ENS\n关作中文\n中国邮政速递物选\n自类产品务\n服苏文行业城决方食民服务制关于我们集站\n奇内地\n邮件号直沟直询能果\n地入,1个级续20个排持号(多个强分空情成与F)\n邮件物迹\n资台\n生\n★☆ 4.91\n+\n邦件号：1285261070703\n在线客服\ns8 -In 0\n不门\n 广\n广k\nQ换\n科号查湾\n山市印\nDA\n市\nX5\n20254年\n06月19日\n送中\n09:37广附市，快正在源送中，请形等持，保电法通，准备签者，加有超的动电联快\n12:25\n广图志，您的快件已代签表【寄排人微收]，或为退应坚者件人，如有经电联换通\n员【电话：13922266917]，有事矿线，少一次投银，多感8，中国部改将全心可\n护物的低,质普电话11183,\n诺员【信超母，电话：13322266917]成旗路【电话：020-83818510】，监督电话\n11183,\n时打天17小时\n服务支牌\n送中\n务查调\n 案户H下线\n个人\n06月15日\n09:03广附市，快件到达[广热市中区染华烫投部】\n05:07广附击，换件已在[广款空中]完成分，准氨发出\n20:53广账市，软离开[广账市中区东高控控的】，正在发往[广指放空中心】\n20:13广市,续件已程[广的市中区乐追医强投型】 完成分苏,准数出\n17:34广面市，已完成遗跑快件的分技，准备发出\n深送异\n1225广附市，医表片人范衣，快件格延面等件人，知有限与评电联性品[电\n磊：18922183735】.股省98电11183,",
      "method": "region_first",
      "duration": 38.24516677856445,
      "region_attempts": [
        {
          "region": "责令号区域",
          "region_key": "notice_header",
          "method": "region:责令号区域",
          "duration": 38.24516677856445,
          "text_length": 671,
          "text": "2025/6/23 10:45\n中国邮政速递物流\n155****9772\nR8ENS\n关作中文\n中国邮政速递物选\n自类产品务\n服苏文行业城决方食民服务制关于我们集站\n奇内地\n邮件号直沟直询能果\n地入,1个级续20个排持号(多个强分空情成与F)\n邮件物迹\n资台\n生\n★☆ 4.91\n+\n邦件号：1285261070703\n在线客服\ns8 -In 0\n不门\n 广\n广k\nQ换\n科号查湾\n山市印\nDA\n市\nX5\n20254年\n06月19日\n送中\n09:37广附市，快正在源送中，请形等持，保电法通，准备签者，加有超的动电联快\n12:25\n广图志，您的快件已代签表【寄排人微收]，或为退应坚者件人，如有经电联换通\n员【电话：13922266917]，有事矿线，少一次投银，多感8，中国部改将全心可\n护物的低,质普电话11183,\n诺员【信超母，电话：13322266917]成旗路【电话：020-83818510】，监督电话\n11183,\n时打天17小时\n服务支牌\n送中\n务查调\n 案户H下线\n个人\n06月15日\n09:03广附市，快件到达[广热市中区染华烫投部】\n05:07广附击，换件已在[广款空中]完成分，准氨发出\n20:53广账市，软离开[广账市中区东高控控的】，正在发往[广指放空中心】\n20:13广市,续件已程[广的市中区乐追医强投型】 完成分苏,准数出\n17:34广面市，已完成遗跑快件的分技，准备发出\n深送异\n1225广附市，医表片人范衣，快件格延面等件人，知有限与评电联性品[电\n磊：18922183735】.股省98电11183,"
        }
      ],
      "region_stats": {
        "attempt_count": 1,
        "total_duration": 38.2452,
        "max_text_length": 671,
        "total_text_length": 671,
        "regions": [
          "责令号区域"
        ]
      },
      "region_text_length": 612,
      "fallback_used": false,
      "fallback_trigger_reason": null,
      "notice_matched": false,
      "boundary_detected": false,
      "marker_detected": false,
      "region_usable": false
    },
    {
      "page": 8,
      "text": "",
      "original_text": "",
      "method": "blank_page_skipped",
      "duration": 0,
      "region_attempts": [],
      "region_stats": {
        "attempt_count": 0,
        "total_duration": 0,
        "max_text_length": 0,
        "total_text_length": 0,
        "regions": []
      },
      "region_text_length": 0,
      "fallback_used": false,
      "fallback_trigger_reason": null,
      "notice_matched": false,
      "boundary_detected": false,
      "marker_detected": false,
      "region_usable": false
    },
    {
      "page": 9,
      "text": "广州住房公积金管理中心\n责令限期办理决定书\n穗公积金中心越秀责字〔2024〕914号\n名称：广州市严静殡葬服务有限公司\n统一社会信用代码：91440101MA5C4HHP8E\n地址：广州市越秀区寺右二马路25号四层454\n经查，你单位未按规定为王柱华缴存2022年07月至2023年06月期间的住房公积金，根据《住房公积金管理条例》(1999年4月3日国务院令第262号发\n布施行，2002年3月24日国务院令第350号第-次修订，2019年3月24日国\n务院令第710号第二次修订)第二条、第十三条、第十五条、第十六条、第十七条、\n第十八条、第十九条、第二十条、第三十七条、第三十八条、第四十七条、《关\n于住房公积金管理若千具体问题的指导意见》(建金管(2005)5号)第六条、《关\n于住房公积金管理几个具体问题的通知》(建金管[2006]52号)等有关规定，\n责令你单位履行以下义务：\n请在收到本决定书之日起10个工作日内为你单位王柱华补缴2022年07月\n至2023年06月期间的单位应缴存部分住房公积金合计2748元到职工住房公积",
      "original_text": "广州住房公积金管理中心\n责令限期办理决定书\n穗公积金中心越秀责字【2024】914号\n名称：广州市严静殡葬服务有限公司\n统一社会信用代码：91440101MA5C4HHP8E\n地址：广州市越秀区寺右二马路25号四层454\n经查，你单位未按规定为王柱华缴存2022年07月至2023年06月期间的住\n房公积金，根据《住房公积金管理条例》（1999年4月3日国务院令第262号发\n布施行，2002年3月24日国务院令第350号第-次修订，2019年3月24日国\n务院令第710号第二次修订）第二条、第十三条、第十五条、第十六条、第十七条、\n第十八条、第十九条、第二十条、第三十七条、第三十八条、第四十七条、《关\n于住房公积金管理若千具体问题的指导意见》（建金管（2005）5号）第六条、《关\n于住房公积金管理几个具体问题的通知》（建金管【2006]52号）等有关规定，\n责令你单位履行以下义务：\n请在收到本决定书之日起10个工作日内为你单位王柱华补缴2022年07月\n至2023年06月期间的单位应缴存部分住房公积金合计2748元到职工住房公积",
      "method": "region_first",
      "duration": 21.739336490631104,
      "region_attempts": [
        {
          "region": "责令号区域",
          "region_key": "notice_header",
          "method": "region:责令号区域",
          "duration": 21.739336490631104,
          "text_length": 470,
          "text": "广州住房公积金管理中心\n责令限期办理决定书\n穗公积金中心越秀责字【2024】914号\n名称：广州市严静殡葬服务有限公司\n统一社会信用代码：91440101MA5C4HHP8E\n地址：广州市越秀区寺右二马路25号四层454\n经查，你单位未按规定为王柱华缴存2022年07月至2023年06月期间的住\n房公积金，根据《住房公积金管理条例》（1999年4月3日国务院令第262号发\n布施行，2002年3月24日国务院令第350号第-次修订，2019年3月24日国\n务院令第710号第二次修订）第二条、第十三条、第十五条、第十六条、第十七条、\n第十八条、第十九条、第二十条、第三十七条、第三十八条、第四十七条、《关\n于住房公积金管理若千具体问题的指导意见》（建金管（2005）5号）第六条、《关\n于住房公积金管理几个具体问题的通知》（建金管【2006]52号）等有关规定，\n责令你单位履行以下义务：\n请在收到本决定书之日起10个工作日内为你单位王柱华补缴2022年07月\n至2023年06月期间的单位应缴存部分住房公积金合计2748元到职工住房公积"
        }
      ],
      "region_stats": {
        "attempt_count": 1,
        "total_duration": 21.7393,
        "max_text_length": 470,
        "total_text_length": 470,
        "regions": [
          "责令号区域"
        ]
      },
      "region_text_length": 455,
      "fallback_used": false,
      "fallback_trigger_reason": null,
      "notice_matched": false,
      "boundary_detected": false,
      "marker_detected": false,
      "region_usable": false
    },
    {
      "page": 10,
      "text": "",
      "original_text": "",
      "method": "blank_page_skipped",
      "duration": 0,
      "region_attempts": [],
      "region_stats": {
        "attempt_count": 0,
        "total_duration": 0,
        "max_text_length": 0,
        "total_text_length": 0,
        "regions": []
      },
      "region_text_length": 0,
      "fallback_used": false,
      "fallback_trigger_reason": null,
      "notice_matched": false,
      "boundary_detected": false,
      "marker_detected": false,
      "region_usable": false
    }
  ],
  "total_pages": 10,
  "filename": "1.pdf",
  "method": "region_first_sequential",
  "total_duration": 126.01011639999342,
  "fallback_pages": 0,
  "region_pages": 5,
  "optimization_strategy": "region_first_sequential",
  "stopped_early": false,
  "selected_notice": null,
  "selected_page": null,
  "selected_root_notice": null,
  "candidate_notices": [],
  "performance_summary": {
    "doc_type": "责催",
    "file_name": "1.pdf",
    "page_count": 10,
    "total_duration": 126.0101,
    "fallback_pages": 0,
    "fallback_rate": 0.0,
    "region_attempts_total": 5,
    "region_ocr_duration_total": 113.911,
    "slowest_page": {
      "page": 7,
      "duration": 38.2452,
      "method": "region_first",
      "fallback_used": false,
      "fallback_trigger_reason": null
    }
  },
  "matched_target": "7-责催-穗公积金中心越秀责字（2024）914-1号.pdf",
  "matched_target_notice": "穗公积金中心越秀责字〔2024〕914-1号",
  "export_match_type": "fuzzy",
  "same_root_remap": true,
  "export_match_similarity": 0.9223809523809523,
  "same_root_selected_notice": "穗公积金中心越秀责字〔2024〕914号"
}